lake_loader/__init__.py
lake_loader/base/__init__.py
lake_loader/base/loader.py
lake_loader/base/parser.py
lake_loader/main.py
lake_loader/telegram/__init__.py
lake_loader/telegram/loader.py
lake_loader/telegram/parser.py
schema/telegram_v1.json
lake_loader-1.0.20230329232345.dist-info/entry_points.txt
lake_loader-1.0.20230329232345.dist-info/WHEEL
lake_loader-1.0.20230329232345.dist-info/METADATA
lake_loader-1.0.20230329232345.dist-info/RECORD
