Metadata-Version: 2.1
Name: lake-loader
Version: 1.0.20230329232345
Summary: 
Author: Lia Bozarth
Author-email: liafan@uw.edu
Requires-Python: >=3.9
Classifier: Programming Language :: Python :: 3
Classifier: Programming Language :: Python :: 3.9
Classifier: Programming Language :: Python :: 3.10
Classifier: Programming Language :: Python :: 3.11
Requires-Dist: confluent_kafka (>=2.0.0,<3.0.0)
Requires-Dist: pyspark (>=3.3.2,<4.0.0)
Requires-Dist: sharedutils (>=1.1,<1.2)
